musisort
