Metadata-Version: 2.1
Name: musisort
Version: 1.1.0
Summary: Automatic Music Categorization Tool
Home-page: https://github.com/ReadyResearchers/AutoMusicSort
Author: Garrison Vanzin
Author-email: vanzing@allegheny.edu
License: MIT License
Keywords: musisort
Platform: UNKNOWN
Classifier: Development Status :: 1 - Planning
License-File: LICENSE
